LICENSE
README.md
setup.py
amazon_scraper_in/__init__.py
amazon_scraper_in.egg-info/PKG-INFO
amazon_scraper_in.egg-info/SOURCES.txt
amazon_scraper_in.egg-info/dependency_links.txt
amazon_scraper_in.egg-info/requires.txt
amazon_scraper_in.egg-info/top_level.txt