Metadata-Version: 2.1
Name: amazon-scraper-in
Version: 0.0.0
Summary: A python library to scrape data on Amazon.
Home-page: UNKNOWN
Author: DataKund
Author-email: datakund@gmail.com
License: Apache License 2.0
Keywords: amazon title price link product python bot_studio automation search scraper scrape
Platform: UNKNOWN
License-File: LICENSE
